jtagtools/__init__.py
jtagtools/bits/__init__.py
jtagtools/jtag/__init__.py
jtagtools/jtag/controller.py
jtagtools/jtag/engine.py
jtagtools/jtag/error.py
jtagtools/jtag/machine.py
jtagtools/rbb/__init__.py
jtagtools/rbb/bitbang.py
pyjtagtools-0.11.1.dist-info/licenses/LICENSE
pyjtagtools-0.11.1.dist-info/METADATA
pyjtagtools-0.11.1.dist-info/WHEEL
pyjtagtools-0.11.1.dist-info/top_level.txt
pyjtagtools-0.11.1.dist-info/RECORD
