Metadata-Version: 2.4
Name: pyjtagtools
Version: 0.11.1
Summary: JTAG engine and tools
Home-page: http://github.com/eblot/pyjtagtools
Author: Emmanuel Blot
Author-email: emmanuel.blot@free.fr
Maintainer: Emmanuel Blot
Maintainer-email: emmanuel.blot@free.fr
License: Apache 2
Keywords: jtag,bitmanip
Classifier: Development Status :: 3 - Alpha
Classifier: Environment :: Other Environment
Classifier: Natural Language :: English
Classifier: Intended Audience :: Developers
Classifier: License :: OSI Approved :: Apache Software License
Classifier: Operating System :: MacOS :: MacOS X
Classifier: Operating System :: POSIX
Classifier: Programming Language :: Python :: 3.9
Classifier: Programming Language :: Python :: 3.10
Classifier: Programming Language :: Python :: 3.11
Classifier: Programming Language :: Python :: 3.12
Classifier: Programming Language :: Python :: 3.13
Classifier: Topic :: Software Development :: Libraries :: Python Modules
Classifier: Topic :: Software Development :: Debuggers
Requires-Python: >=3.9
License-File: LICENSE
Dynamic: author
Dynamic: author-email
Dynamic: classifier
Dynamic: description
Dynamic: description-content-type
Dynamic: home-page
Dynamic: keywords
Dynamic: license
Dynamic: license-file
Dynamic: maintainer
Dynamic: maintainer-email
Dynamic: requires-python
Dynamic: summary
